{
	"meta": {
		"title": "Customer List"
	},
	"items": [
		[
			{
				"cust_no": 1001,
				"customer": "Signature Design",
				"contact_first": "Dale J.",
				"contact_last": "Little",
				"phone_no": "(619) 530-2710",
				"address_line1": "15500 Pacific Heights Blvd.",
				"address_line2": null,
				"city": "San Diego",
				"state_province": "CA",
				"country": "USA",
				"postal_code": "92121",
				"on_hold": null,
				"rows": [
					{
						"product": "Pizza Margherita",
						"price": 10,
						"quantity": 6
					},
					{
						"product": "Spaghetti Carbonara",
						"price": 12,
						"quantity": 7
					},
					{
						"product": "Bucatini Amatriciana",
						"price": 11,
						"quantity": 4
					},
					{
						"product": "Tiramisù",
						"price": 5,
						"quantity": 3
					}
				]
			},
			{
				"cust_no": 1002,
				"customer": "DALLAS TECHNOLOGIES",
				"contact_first": "Glenno",
				"contact_last": "Brown",
				"phone_no": "(214) 960-2233",
				"address_line1": "P. O. Box 47000",
				"address_line2": "",
				"city": "Dallas",
				"state_province": "TX",
				"country": "USA",
				"postal_code": "75205",
				"on_hold": "*",
				"rows": [
					{
						"product": "Pizza Margherita",
						"price": 10,
						"quantity": 5
					},
					{
						"product": "Spaghetti Carbonara",
						"price": 12,
						"quantity": 4
					},
					{
						"product": "Bucatini Amatriciana",
						"price": 11,
						"quantity": 3
					},
					{
						"product": "Tiramisù",
						"price": 5,
						"quantity": 2
					}
				]
			},
			{
				"cust_no": 1003,
				"customer": "Buttle, Griffith and Co.",
				"contact_first": "James",
				"contact_last": "Buttle",
				"phone_no": "(617) 488-1864",
				"address_line1": "2300 Newbury Street",
				"address_line2": "Suite 101",
				"city": "Boston",
				"state_province": "MA",
				"country": "USA",
				"postal_code": "02115",
				"on_hold": null,
				"rows": [
					{
						"product": "Pizza Margherita",
						"price": 10,
						"quantity": 8
					},
					{
						"product": "Spaghetti Carbonara",
						"price": 12,
						"quantity": 9
					},
					{
						"product": "Bucatini Amatriciana",
						"price": 11,
						"quantity": 1
					},
					{
						"product": "Tiramisù",
						"price": 5,
						"quantity": 3
					}
				]
			},
			{
				"cust_no": 1004,
				"customer": "Central Bank",
				"contact_first": "Elizabeth",
				"contact_last": "Brocket",
				"phone_no": "61 211 99 88",
				"address_line1": "66 Lloyd Street",
				"address_line2": null,
				"city": "Manchester",
				"state_province": "",
				"country": "England",
				"postal_code": "M2 3LA",
				"on_hold": null,
				"rows": [
					{
						"product": "Pizza Margherita",
						"price": 10,
						"quantity": 7
					},
					{
						"product": "Spaghetti Carbonara",
						"price": 12,
						"quantity": 8
					},
					{
						"product": "Bucatini Amatriciana",
						"price": 11,
						"quantity": 2
					},
					{
						"product": "Tiramisù",
						"price": 5,
						"quantity": 3
					}
				]
			},
			{
				"cust_no": 1005,
				"customer": "DT Systems, LTD.",
				"contact_first": "Tai",
				"contact_last": "Wu",
				"phone_no": "(852) 850 43 98",
				"address_line1": "400 Connaught Road",
				"address_line2": null,
				"city": "Central Hong Kong",
				"state_province": null,
				"country": "Hong Kong",
				"postal_code": null,
				"on_hold": null,
				"rows": [
					{
						"product": "Pizza Margherita",
						"price": 10,
						"quantity": 1
					},
					{
						"product": "Spaghetti Carbonara",
						"price": 12,
						"quantity": 9
					},
					{
						"product": "Bucatini Amatriciana",
						"price": 11,
						"quantity": 4
					},
					{
						"product": "Tiramisù",
						"price": 5,
						"quantity": 1
					}
				]
			},
			{
				"cust_no": 1006,
				"customer": "DataServe International",
				"contact_first": "Tomas",
				"contact_last": "Bright",
				"phone_no": "(613) 229 3323",
				"address_line1": "2000 Carling Avenue",
				"address_line2": "Suite 150ccc",
				"city": "Ottawa",
				"state_province": "ON",
				"country": "Canada",
				"postal_code": "K1V 9G1",
				"on_hold": null,
				"rows": [
					{
						"product": "Pizza Margherita",
						"price": 10,
						"quantity": 9
					},
					{
						"product": "Spaghetti Carbonara",
						"price": 12,
						"quantity": 3
					},
					{
						"product": "Bucatini Amatriciana",
						"price": 11,
						"quantity": 2
					}
				]
			},
			{
				"cust_no": 1007,
				"customer": "Mrs. Beauvais",
				"contact_first": "",
				"contact_last": "Mrs. Beauvais",
				"phone_no": null,
				"address_line1": "P.O. Box 22743",
				"address_line2": null,
				"city": "Pebble Beach",
				"state_province": "CA",
				"country": "USA",
				"postal_code": "93953",
				"on_hold": null,
				"rows": [
					{
						"product": "Pizza Margherita",
						"price": 10,
						"quantity": 7
					},
					{
						"product": "Spaghetti Carbonara",
						"price": 12,
						"quantity": 10
					},
					{
						"product": "Bucatini Amatriciana",
						"price": 11,
						"quantity": 2
					},
					{
						"product": "Tiramisù",
						"price": 5,
						"quantity": 3
					}
				]
			},
			{
				"cust_no": 1008,
				"customer": "Anini Vacation Rentals",
				"contact_first": "Leilani",
				"contact_last": "Briggs",
				"phone_no": "(808) 835-7605",
				"address_line1": "3320 Lawai Road",
				"address_line2": null,
				"city": "Lihue",
				"state_province": "HI",
				"country": "USA",
				"postal_code": "96766",
				"on_hold": null,
				"rows": [
					{
						"product": "Pizza Margherita",
						"price": 10,
						"quantity": 2
					},
					{
						"product": "Spaghetti Carbonara",
						"price": 12,
						"quantity": 8
					},
					{
						"product": "Bucatini Amatriciana",
						"price": 11,
						"quantity": 3
					},
					{
						"product": "Tiramisù",
						"price": 5,
						"quantity": 1
					}
				]
			},
			{
				"cust_no": 1009,
				"customer": "Max",
				"contact_first": "Max",
				"contact_last": "",
				"phone_no": "22 01 23",
				"address_line1": "1 Emerald Cove",
				"address_line2": "",
				"city": "Turtle Island",
				"state_province": "",
				"country": "Fiji",
				"postal_code": "",
				"on_hold": "*",
				"rows": [
					{
						"product": "Pizza Margherita",
						"price": 10,
						"quantity": 8
					}
				]
			},
			{
				"cust_no": 1010,
				"customer": "MPM Corporation",
				"contact_first": "Miwako",
				"contact_last": "Miyamoto",
				"phone_no": "3 880 77 19",
				"address_line1": "2-64-7 Sasazuka",
				"address_line2": null,
				"city": "Tokyo",
				"state_province": null,
				"country": "Japan",
				"postal_code": "150",
				"on_hold": null,
				"rows": [
					{
						"product": "Pizza Margherita",
						"price": 10,
						"quantity": 3
					}
				]
			},
			{
				"cust_no": 1011,
				"customer": "Dynamic Intelligence Corp",
				"contact_first": "Victor",
				"contact_last": "Granges",
				"phone_no": "01 221 16 50",
				"address_line1": "Florhofgasse 10",
				"address_line2": null,
				"city": "Zurich",
				"state_province": null,
				"country": "Switzerland",
				"postal_code": "8005",
				"on_hold": null,
				"rows": [
					{
						"product": "Pizza Margherita",
						"price": 10,
						"quantity": 5
					},
					{
						"product": "Spaghetti Carbonara",
						"price": 12,
						"quantity": 6
					},
					{
						"product": "Bucatini Amatriciana",
						"price": 11,
						"quantity": 4
					},
					{
						"product": "Tiramisù",
						"price": 5,
						"quantity": 3
					}
				]
			},
			{
				"cust_no": 1012,
				"customer": "3D-Pad Corp.",
				"contact_first": "Michelle",
				"contact_last": "Roche",
				"phone_no": "1 43 60 61",
				"address_line1": "22 Place de la Concorde",
				"address_line2": null,
				"city": "Paris",
				"state_province": null,
				"country": "France",
				"postal_code": "75008",
				"on_hold": null,
				"rows": [
					{
						"product": "Pizza Margherita",
						"price": 10,
						"quantity": 2
					},
					{
						"product": "Spaghetti Carbonara",
						"price": 12,
						"quantity": 1
					},
					{
						"product": "Bucatini Amatriciana",
						"price": 11,
						"quantity": 2
					},
					{
						"product": "Tiramisù",
						"price": 5,
						"quantity": 3
					}
				]
			},
			{
				"cust_no": 1013,
				"customer": "Lorenzi Export, Ltd.",
				"contact_first": "Andreas",
				"contact_last": "Lorenzi",
				"phone_no": "02 404 6284",
				"address_line1": "Via Eugenia, 15",
				"address_line2": null,
				"city": "Milan",
				"state_province": null,
				"country": "Italy",
				"postal_code": "20124",
				"on_hold": null,
				"rows": [
					{
						"product": "Pizza Margherita",
						"price": 10,
						"quantity": 9
					},
					{
						"product": "Spaghetti Carbonara",
						"price": 12,
						"quantity": 2
					},
					{
						"product": "Bucatini Amatriciana",
						"price": 11,
						"quantity": 4
					},
					{
						"product": "Tiramisù",
						"price": 5,
						"quantity": 4
					}
				]
			},
			{
				"cust_no": 1014,
				"customer": "Dyno Consulting",
				"contact_first": "Greta",
				"contact_last": "Hessels",
				"phone_no": "02 500 5940",
				"address_line1": "Rue Royale 350",
				"address_line2": null,
				"city": "Brussels",
				"state_province": null,
				"country": "Belgium",
				"postal_code": "1210",
				"on_hold": null,
				"rows": [
					{
						"product": "Pizza Margherita",
						"price": 10,
						"quantity": 3
					},
					{
						"product": "Spaghetti Carbonara",
						"price": 12,
						"quantity": 8
					},
					{
						"product": "Bucatini Amatriciana",
						"price": 11,
						"quantity": 3
					},
					{
						"product": "Tiramisù",
						"price": 5,
						"quantity": 4
					}
				]
			},
			{
				"cust_no": 1015,
				"customer": "GeoTech Inc.",
				"contact_first": "K.M.",
				"contact_last": "Neppelenbroek",
				"phone_no": "(070) 44 91 18",
				"address_line1": "P.0.Box 702",
				"address_line2": null,
				"city": "Den Haag",
				"state_province": null,
				"country": "Netherlands",
				"postal_code": "2514",
				"on_hold": null,
				"rows": [
					{
						"product": "Pizza Margherita",
						"price": 10,
						"quantity": 7
					},
					{
						"product": "Spaghetti Carbonara",
						"price": 12,
						"quantity": 2
					},
					{
						"product": "Bucatini Amatriciana",
						"price": 11,
						"quantity": 1
					},
					{
						"product": "Tiramisù",
						"price": 5,
						"quantity": 3
					}
				]
			}
		]
	]
}
